{"cookies": [{"name": "visitor_id", "value": "NY3KVPNLOPSIU90HXG7DV6R28K9FJLLX", "domain": "supplier.getyourguide.com", "path": "/", "expires": -1, "httpOnly": true, "secure": true, "sameSite": "Lax"}, {"name": "supplier_locale_code", "value": "en-US", "domain": "supplier.getyourguide.com", "path": "/", "expires": -1, "httpOnly": false, "secure": true, "sameSite": "Lax"}, {"name": "__cf_bm", "value": ".cVQ9JLVi9fORbrwTcwqoHj18mMS3p5ulyugGUZMQpE-1776294355-1.0.1.1-IDZ8h02a6_9xz4Ot.hjfp5OhVASayz8NX23Z9i9TTytF3WDk46HLBSjJtpsDRlk_FVTOBZXxUMVDfHxzhemytNKJ2hw3hTtz4X_n5vO3LGU", "domain": ".supplier.getyourguide.com", "path": "/", "expires": 1776296155.452075, "httpOnly": true, "secure": true, "sameSite": "None"}, {"name": "_hjSession_1199376", "value": "eyJpZCI6Ijg1MGM3YzcwLTI4ZWYtNDVmYy05YTEyLTJjMjUyN2JlMjhiNyIsImMiOjE3NzYyOTQzNTYxMjIsInMiOjAsInIiOjAsInNiIjowLCJzciI6MCwic2UiOjAsImZzIjoxLCJzcCI6MH0=", "domain": ".getyourguide.com", "path": "/", "expires": 1776296156, "httpOnly": false, "secure": true, "sameSite": "None"}, {"name": "is_embedded", "value": "false", "domain": "supplier.getyourguide.com", "path": "/", "expires": -1, "httpOnly": false, "secure": false, "sameSite": "Lax"}, {"name": "_hjSessionUser_1199376", "value": "eyJpZCI6ImMzZmNiMjYxLWI4ZDktNTE3Ni1hNTc0LTAyZjJkODY0MjNhZiIsImNyZWF0ZWQiOjE3NzYyOTQzNTYxMTMsImV4aXN0aW5nIjp0cnVlfQ==", "domain": ".getyourguide.com", "path": "/", "expires": 1807830544, "httpOnly": false, "secure": true, "sameSite": "None"}, {"name": "__cf_bm", "value": "ggyB.FV_i1_zkL1lI4OoVf3z6t5t7icIxnaggJB.zNo-1776294363-1.0.1.1-T8wpimzJe3_9FIpv9MlG8G0IHM4m4SFwXjQyLcFmWWLgOLRfFcdfusGk2WTf1IsGKUoxiwCTjQdD8ygAOF0gQGSFQJV3yH6OIQzr0nhgBjU", "domain": ".travelers-api.getyourguide.com", "path": "/", "expires": 1776296163.283942, "httpOnly": true, "secure": true, "sameSite": "None"}, {"name": "ab.storage.deviceId.c36da9fe-8874-4c02-8a45-d9edace47cff", "value": "g%3A7aa82dfd-b356-1791-caed-a324701eec2e%7Ce%3Aundefined%7Cc%3A1776294367463%7Cl%3A1776294391456", "domain": ".getyourguide.com", "path": "/", "expires": 1810854544, "httpOnly": false, "secure": false, "sameSite": "Lax"}, {"name": "ab.storage.userId.c36da9fe-8874-4c02-8a45-d9edace47cff", "value": "g%3A1038239%7Ce%3Aundefined%7Cc%3A1776294391455%7Cl%3A1776294391457", "domain": ".getyourguide.com", "path": "/", "expires": 1810854544, "httpOnly": false, "secure": false, "sameSite": "Lax"}, {"name": "supplier_id", "value": "707722", "domain": "supplier.getyourguide.com", "path": "/", "expires": -1, "httpOnly": false, "secure": false, "sameSite": "Lax"}, {"name": "_iidt", "value": "/AXdkQFTcQskhEv8jkK51aR9X5c/hpkupepxbropRcjqBgT6xYGF/ykDg2DEmBoKDRSxPa1DmwKOKlljZ8PDInhhYm/OVD3lTWGzgtrvCa5sbIZFYw==", "domain": ".withpersona.com", "path": "/", "expires": 1807830393.146166, "httpOnly": true, "secure": true, "sameSite": "None"}, {"name": "apVId", "value": "51st8xjodtispujcvjmgt0r93oo4gaky", "domain": "supplier.getyourguide.com", "path": "/", "expires": -1, "httpOnly": false, "secure": true, "sameSite": "Lax"}, {"name": "ab.storage.sessionId.c36da9fe-8874-4c02-8a45-d9edace47cff", "value": "g%3Ad59dc237-dbce-dd14-1743-f9dede882c55%7Ce%3A1776296344674%7Cc%3A1776294391456%7Cl%3A1776294544674", "domain": ".getyourguide.com", "path": "/", "expires": 1810854544, "httpOnly": false, "secure": false, "sameSite": "Lax"}, {"name": "_dd_s", "value": "aid=c35d74b8-5ad6-45aa-a757-31f80f41e86c&rum=0&expire=1776295475305", "domain": "supplier.getyourguide.com", "path": "/", "expires": 1807830575, "httpOnly": false, "secure": false, "sameSite": "Strict"}], "origins": [{"origin": "https://supplier.getyourguide.com", "localStorage": [{"name": "ab.storage.triggers.c36da9fe-8874-4c02-8a45-d9edace47cff", "value": "{\"v\":[]}"}, {"name": "ab.storage.userId.c36da9fe-8874-4c02-8a45-d9edace47cff", "value": "{\"v\":\"g:1038239|e:undefined|c:1776294391455|l:1776294391457\"}"}, {"name": "ab.storage.device.c36da9fe-8874-4c02-8a45-d9edace47cff", "value": "{\"v\":{\"browser\":\"Chrome\",\"browser_version\":\"145\",\"os_version\":\"Windows\",\"locale\":\"en-us\",\"time_zone\":\"UTC\",\"user_agent\":\"Mozilla/5.0 (Windows NT 10.0; Win64; x64) AppleWebKit/537.36 (KHTML, like Gecko) Chrome/120.0.0.0 Safari/537.36\"}}"}, {"name": "66d0858efe670c71fc7df867.clientId", "value": "467f978f553a41d782cd2ee8172f517f"}, {"name": "ab.storage.messagingSessionStart.c36da9fe-8874-4c02-8a45-d9edace47cff", "value": "{\"v\":1776294367463}"}, {"name": "ab.storage.requestAttempts.c36da9fe-8874-4c02-8a45-d9edace47cff", "value": "{\"v\":{\"d\":1,\"ff\":1}}"}, {"name": "ab.storage.sessionId.c36da9fe-8874-4c02-8a45-d9edace47cff", "value": "{\"v\":\"g:d59dc237-dbce-dd14-1743-f9dede882c55|e:1776296344674|c:1776294391456|l:1776294544674\"}"}, {"name": "ZD-suid", "value": "{\"id\":\"fb161516f6fa47faa4b79a696e1de7f2\",\"expiry\":1776295444907,\"tabs\":{\"count\":1,\"expiry\":0}}"}, {"name": "isZendeskScriptLoaded", "value": "true"}, {"name": "ucData", "value": "{\"gcm\":{\"adsDataRedaction\":true,\"adStorage\":\"denied\",\"adPersonalization\":\"denied\",\"adUserData\":\"denied\",\"analyticsStorage\":\"denied\"},\"consent\":{\"services\":{\"Xl0HIOViY\":{\"name\":\"Datadog Real User Monitoring\",\"consent\":true},\"HkPBYFofN\":{\"name\":\"Google Fonts\",\"consent\":true},\"R2gyvn3ugawW0t\":{\"name\":\"Google Hosted Libraries\",\"consent\":true},\"S1pcEj_jZX\":{\"name\":\"Google Maps\",\"consent\":true},\"XJGT8f-58\":{\"name\":\"Google Sign-In\",\"consent\":true},\"BJ59EidsWQ\":{\"name\":\"Google Tag Manager\",\"consent\":true},\"rJJjcVouoZ7\":{\"name\":\"gstatic.com\",\"consent\":true},\"H1Vl5NidjWX\":{\"name\":\"Usercentrics Consent Management Platform\",\"consent\":true},\"54s8nFgf\":{\"name\":\"Zendesk\",\"consent\":true},\"ko1w5PpFl\":{\"name\":\"Facebook Pixel\",\"consent\":false},\"twMyStLkn\":{\"name\":\"Google Ads Conversion Tracking\",\"consent\":false},\"87JYasXPF\":{\"name\":\"Google Analytics 4\",\"consent\":false},\"S1kgcNo_j-m\":{\"name\":\"Hotjar\",\"consent\":false},\"JQ2XQxIk\":{\"name\":\"LinkedIn Insight Tag\",\"consent\":false},\"rH1vNPCFR\":{\"name\":\"Sentry\",\"consent\":false}}},\"ui\":{\"language\":\"en\"}}"}, {"name": "ab.storage.ffLastRefreshAt.c36da9fe-8874-4c02-8a45-d9edace47cff", "value": "{\"v\":1776294391671}"}, {"name": "ZD-buid", "value": "467f978f553a41d782cd2ee8172f517f"}, {"name": "isZendeskChatAuthenticated", "value": "true"}, {"name": "zendeskAuthToken", "value": "eyJhbGciOiJIUzUxMiIsInR5cCI6IkpXVCIsImtpZCI6ImFwcF82NmQ4NTIzOWM1NzkwMzhlYzYxZGYwOTEifQ.eyJzY29wZSI6InVzZXIiLCJleHRlcm5hbF9pZCI6IkdZR1NVUFBMSUVSQUNDT1VOVDEwMzgyMzkiLCJlbWFpbF92ZXJpZmllZCI6dHJ1ZSwiaWF0IjoxNzc2Mjk0NTQ0LCJqdGkiOiIwYmU2Y2QzYi01ZTc0LTQ2ZmYtODVmYS1iYjI5NDU3N2U1OTEiLCJuYW1lIjoiQWhtZWQgRWxraGF0aWIiLCJlbWFpbCI6ImFobWVkLmVsa2hhdGliQGZ0c3RyYXZlbHMuY29tIn0.qohElNcdLkpvMjhNh2elssApiUk6ei6TSDJnh0-5Chtd5qjbWyrabuGFRLDcIAulW1GFv5o2pT8vqZoXE0Zwew"}, {"name": "zendeskChatStatus", "value": "solved"}, {"name": "sentinel_data_obj_sent", "value": "{\"707722\":true}"}, {"name": "66d0858efe670c71fc7df867.appUserId", "value": "696779147e0e1cf5f001f1c9"}, {"name": "66d0858efe670c71fc7df867.surname", "value": "Elkhatib"}, {"name": "ab.storage.lastReqToEndpoint.c36da9fe-8874-4c02-8a45-d9edace47cff", "value": "{\"v\":{\"d\":1776294544675,\"ff\":1776294391465}}"}, {"name": "ab.storage.session_id_for_cached_metadata.c36da9fe-8874-4c02-8a45-d9edace47cff", "value": "{\"v\":\"d59dc237-dbce-dd14-1743-f9dede882c55\"}"}, {"name": "66d0858efe670c71fc7df867.email", "value": "ahmed.elkhatib@ftstravels.com"}, {"name": "ab.storage.sdk_metadata.c36da9fe-8874-4c02-8a45-d9edace47cff", "value": "{\"v\":[\"npm\"]}"}, {"name": "ab.storage.globalRateLimitCurrentTokenCount.c36da9fe-8874-4c02-8a45-d9edace47cff", "value": "{\"v\":21}"}, {"name": "ucString", "value": "N4IgbgpgTgzglgewHYgFwEYA0ICucBq08yaIAzAHTroAsFADCNgMbIAuUCANl9AJIATUgDYaAVgjD6NAJwD6AsfQjMIAJgjoAhloBm4sWJm709GWoDss5rt3Nm6ABxbVix+gBGFrTJoWBzB5kxuhi6EwgXFpIAOY4WjEQpBAo2DAQbGxwsWigbACeAA5JqCAA4gAiAAoAShFwQqUeMIVIALQAGgC2AIIAmggAHl0wAFIRkLCIKKXoFhTzwSAAvtg4hQJabBACPWxocxbCar5kwmRqwjJrG1s7AEL5pMgVKfk9PADK0GBwqjARZhQCB3Xb7DAWI4nGhkQyOWHYYEARzwwMaui0XHSaTYWxwANKPQAMkSAPoVACiADk+BSKhECsVSBSOlUiXwAMJ8AAqEQAFloYHzSI4BBAPOcILpHDRJGQaFo1OhhBJhBYPAJdFZHDJmMIIBYIEogjJ9Y4zGRdKbjDRHGoxfRDBYyN4aOE0j8/hBBASANoAXWwMUKzE+cBiSExaAxWIg2Gy2ygLiyJFK+OgKyAA=="}, {"name": "ab.storage.deviceId.c36da9fe-8874-4c02-8a45-d9edace47cff", "value": "{\"v\":\"g:7aa82dfd-b356-1791-caed-a324701eec2e|e:undefined|c:1776294367463|l:1776294391456\"}"}, {"name": "ab.storage.lastSdkReq.c36da9fe-8874-4c02-8a45-d9edace47cff", "value": "{\"v\":1776294544675}"}, {"name": "ab.storage.serverConfig.c36da9fe-8874-4c02-8a45-d9edace47cff", "value": "{\"v\":{\"s\":\"5.1.1\",\"l\":1774361172,\"e\":[],\"a\":[\"20250129_commission_is_tour_6\",\"202501_activ_tours_3defects_campaign\",\"accounts\",\"attributesMap\",\"completedness\",\"dev_tours\",\"exampleArr\",\"exampleArr10\",\"exampleArr2\",\"mql_activities>tours_online\"],\"p\":[],\"m\":21600,\"v\":\"BGWjRIY5UQ_emQBXbcJdUyrKz0N2vDTT_DuZQbnoHe6E6gTIA9m6un60Y-X3Ip0ifxBHjK7oPoHiodrrZwMXr9c=\",\"c\":{\"enabled\":true},\"f\":{\"enabled\":true,\"refresh_rate_limit\":300},\"grl\":{\"capacity\":30,\"enabled\":true,\"endpoint_overrides\":{\"banners/sync\":{\"capacity\":5,\"refill_rate\":180},\"content_cards/sync\":{\"capacity\":5,\"refill_rate\":10},\"push/redeliver\":{\"capacity\":1,\"refill_rate\":180}},\"refill_rate\":30}}}"}, {"name": "zendeskExternalId", "value": "GYGSUPPLIERACCOUNT1038239"}, {"name": "ab.storage.ff.sessionId.c36da9fe-8874-4c02-8a45-d9edace47cff", "value": "{\"v\":\"d59dc237-dbce-dd14-1743-f9dede882c55\"}"}, {"name": "uc:analytics:firedEvents:bspn-XmAYoxmsJ", "value": "[\"CMP_ELIGIBLE\",\"CMP_SHOWN\",\"DENY_ALL\"]"}, {"name": "66d0858efe670c71fc7df867.givenName", "value": "Ahmed"}, {"name": "ab.storage.ff.c36da9fe-8874-4c02-8a45-d9edace47cff", "value": "{\"v\":{}}"}, {"name": "ab.storage.triggers.ts.c36da9fe-8874-4c02-8a45-d9edace47cff", "value": "{\"v\":1776294391862}"}]}, {"origin": "https://web.cmp.usercentrics.eu", "localStorage": [{"name": "ucData_bspn-XmAYoxmsJ", "value": "{\"ucString\":\"N4IgbgpgTgzglgewHYgFwEYA0ICucBq08yaIAzAHTroAsFADCNgMbIAuUCANl9AJIATUgDYaAVgjD6NAJwD6AsfQjMIAJgjoAhloBm4sWJm709GWoDss5rt3Nm6ABxbVix+gBGFrTJoWBzB5kxuhi6EwgXFpIAOY4WjEQpBAo2DAQbGxwsWigbACeAA5JqCAA4gAiAAoAShFwQqUeMIVIALQAGgC2AIIAmggAHl0wAFIRkLCIKKXoFhTzwSAAvtg4hQJabBACPWxocxbCar5kwmRqwjJrG1s7AEL5pMgVKfk9PADK0GBwqjARZhQCB3Xb7DAWI4nGhkQyOWHYYEARzwwMaui0XHSaTYWxwANKPQAMkSAPoVACiADk+BSKhECsVSBSOlUiXwAMJ8AAqEQAFloYHzSI4BBAPOcILpHDRJGQaFo1OhhBJhBYPAJdFZHDJmMIIBYIEogjJ9Y4zGRdKbjDRHGoxfRDBYyN4aOE0j8/hBBASANoAXWwMUKzE+cBiSExaAxWIg2Gy2ygLiyJFK+OgKyAA==\"}"}]}, {"origin": "https://cluster-de.withpersona.com", "localStorage": [{"name": "_vid_t", "value": "NPc9hBG4MhE4oHCmTdpjl+DVZBciw2uWeSpiW/g7jV7m0/0ripevd/f/Y34WaPb7Rjr6MXzIQgyGFOib6UuQ9aECKJf3Rz3NwwheqvljUZBXbqoxEA=="}]}]}